[
    {
        "polygon_coordinates": [
            [
                [
                    -68.879248,
                    -22.284427
                ],
                [
                    -68.879248,
                    -22.284489
                ],
                [
                    -68.879176,
                    -22.284489
                ],
                [
                    -68.879176,
                    -22.284427
                ],
                [
                    -68.879248,
                    -22.284427
                ]
            ]
        ],
        "polygon_type": "Building"
    },
    {
        "polygon_coordinates": [
            [
                [
                    -68.874589,
                    -22.286427
                ],
                [
                    -68.874589,
                    -22.286517
                ],
                [
                    -68.874485,
                    -22.286517
                ],
                [
                    -68.874485,
                    -22.286427
                ],
                [
                    -68.874589,
                    -22.286427
                ]
            ]
        ],
        "polygon_type": "Building"
    },
    {
        "polygon_coordinates": [
            [
                [
                    -68.874682,
                    -22.28759
                ],
                [
                    -68.874682,
                    -22.287794
                ],
                [
                    -68.874454,
                    -22.287794
                ],
                [
                    -68.874454,
                    -22.28759
                ],
                [
                    -68.874682,
                    -22.28759
                ]
            ]
        ],
        "polygon_type": "Building"
    },
    {
        "polygon_coordinates": [
            [
                [
                    -68.87437,
                    -22.28747
                ],
                [
                    -68.87437,
                    -22.287699
                ],
                [
                    -68.874472,
                    -22.287699
                ],
                [
                    -68.874472,
                    -22.28747
                ],
                [
                    -68.87437,
                    -22.28747
                ]
            ]
        ],
        "polygon_type": "Building"
    },
    {
        "polygon_coordinates": [
            [
                [
                    -68.874957,
                    -22.287971
                ],
                [
                    -68.874957,
                    -22.288145
                ],
                [
                    -68.874762,
                    -22.288145
                ],
                [
                    -68.874762,
                    -22.287971
                ],
                [
                    -68.874957,
                    -22.287971
                ]
            ]
        ],
        "polygon_type": "Building"
    },
    {
        "polygon_coordinates": [
            [
                [
                    -68.874693,
                    -22.287886
                ],
                [
                    -68.874693,
                    -22.287951
                ],
                [
                    -68.874771,
                    -22.287951
                ],
                [
                    -68.874771,
                    -22.287886
                ],
                [
                    -68.874693,
                    -22.287886
                ]
            ]
        ],
        "polygon_type": "Building"
    },
    {
        "polygon_coordinates": [
            [
                [
                    -68.874513,
                    -22.287936
                ],
                [
                    -68.874513,
                    -22.288004
                ],
                [
                    -68.874589,
                    -22.288004
                ],
                [
                    -68.874589,
                    -22.287936
                ],
                [
                    -68.874513,
                    -22.287936
                ]
            ]
        ],
        "polygon_type": "Building"
    },
    {
        "polygon_coordinates": [
            [
                [
                    -68.874476,
                    -22.287778
                ],
                [
                    -68.874476,
                    -22.287846
                ],
                [
                    -68.874541,
                    -22.287846
                ],
                [
                    -68.874541,
                    -22.287778
                ],
                [
                    -68.874476,
                    -22.287778
                ]
            ]
        ],
        "polygon_type": "Building"
    },
    {
        "polygon_coordinates": [
            [
                [
                    -68.874496,
                    -22.287835
                ],
                [
                    -68.874496,
                    -22.287897
                ],
                [
                    -68.874554,
                    -22.287897
                ],
                [
                    -68.874554,
                    -22.287835
                ],
                [
                    -68.874496,
                    -22.287835
                ]
            ]
        ],
        "polygon_type": "Building"
    },
    {
        "polygon_coordinates": [
            [
                [
                    -68.874531,
                    -22.287916
                ],
                [
                    -68.874531,
                    -22.287865
                ],
                [
                    -68.874607,
                    -22.287865
                ],
                [
                    -68.874607,
                    -22.287916
                ],
                [
                    -68.874531,
                    -22.287916
                ]
            ]
        ],
        "polygon_type": "Building"
    },
    {
        "polygon_coordinates": [
            [
                [
                    -68.874601,
                    -22.287846
                ],
                [
                    -68.874601,
                    -22.288022
                ],
                [
                    -68.874733,
                    -22.288022
                ],
                [
                    -68.874733,
                    -22.287846
                ],
                [
                    -68.874601,
                    -22.287846
                ]
            ]
        ],
        "polygon_type": "Building"
    },
    {
        "polygon_coordinates": [
            [
                [
                    -68.874501,
                    -22.287474
                ],
                [
                    -68.874501,
                    -22.287601
                ],
                [
                    -68.874569,
                    -22.287601
                ],
                [
                    -68.874569,
                    -22.287474
                ],
                [
                    -68.874501,
                    -22.287474
                ]
            ]
        ],
        "polygon_type": "Building"
    },
    {
        "polygon_coordinates": [
            [
                [
                    -68.874431,
                    -22.287513
                ],
                [
                    -68.874431,
                    -22.28764
                ],
                [
                    -68.874495,
                    -22.28764
                ],
                [
                    -68.874495,
                    -22.287513
                ],
                [
                    -68.874431,
                    -22.287513
                ]
            ]
        ],
        "polygon_type": "Building"
    },
    {
        "polygon_coordinates": [
            [
                [
                    -68.874578,
                    -22.287514
                ],
                [
                    -68.874578,
                    -22.287587
                ],
                [
                    -68.87463,
                    -22.287587
                ],
                [
                    -68.87463,
                    -22.287514
                ],
                [
                    -68.874578,
                    -22.287514
                ]
            ]
        ],
        "polygon_type": "Shed"
    },
    {
        "polygon_coordinates": [
            [
                [
                    -68.874394,
                    -22.287494
                ],
                [
                    -68.874394,
                    -22.287427
                ],
                [
                    -68.874346,
                    -22.287427
                ],
                [
                    -68.874346,
                    -22.287494
                ],
                [
                    -68.874394,
                    -22.287494
                ]
            ]
        ],
        "polygon_type": "Shed"
    }
]